wrappa/__init__.py
wrappa/__main__.py
wrappa/app.py
wrappa/validate.py
wrappa/client/__init__.py
wrappa/client/client.py
wrappa/common/__init__.py
wrappa/common/config.py
wrappa/common/http_utils.py
wrappa/models/__init__.py
wrappa/models/base.py
wrappa/models/file.py
wrappa/models/image.py
wrappa/models/legacy_converter.py
wrappa/models/text.py
wrappa/resources/__init__.py
wrappa/resources/healthcheck.py
wrappa/resources/predict.py
wrappa/resources/predictor.py
wrappa/storage/__init__.py
wrappa/storage/file.py
wrappa-0.4.1.dist-info/LICENSE
wrappa-0.4.1.dist-info/METADATA
wrappa-0.4.1.dist-info/WHEEL
wrappa-0.4.1.dist-info/entry_points.txt
wrappa-0.4.1.dist-info/top_level.txt
wrappa-0.4.1.dist-info/RECORD
